{
  "players": [
    {
      "eraNormFactor": 1.0,
      "id": "p_00-0030506_KC_2021",
      "is_all_pro": true,
      "name": "Travis Kelce",
      "position": "WR",
      "rating": 98,
      "stats": {
        "avgCatchesPerGame": 6.05,
        "avgTargetsPerGame": 8.47,
        "recYPG": 74.9,
        "tdPerGame": 0.632
      },
      "team": "KC",
      "year": 2021
    },
    {
      "eraNormFactor": 1.0,
      "id": "p_00-0031376_KC_2021",
      "name": "Jerick McKinnon",
      "position": "RB",
      "rating": 69,
      "stats": {
        "recYPG": 27.2,
        "rushAttPerGame": 4.6,
        "rushYPG": 21.2,
        "tdPerGame": 0.0
      },
      "team": "KC",
      "year": 2021
    },
    {
      "eraNormFactor": 1.0,
      "id": "p_00-0032775_KC_2021",
      "name": "Demarcus Robinson",
      "position": "WR",
      "rating": 68,
      "stats": {
        "avgCatchesPerGame": 1.71,
        "avgTargetsPerGame": 2.94,
        "recYPG": 20.0,
        "tdPerGame": 0.176
      },
      "team": "KC",
      "year": 2021
    },
    {
      "eraNormFactor": 1.0,
      "id": "p_00-0033040_KC_2021",
      "is_all_pro": true,
      "name": "Tyreek Hill",
      "position": "WR",
      "rating": 98,
      "stats": {
        "avgCatchesPerGame": 6.7,
        "avgTargetsPerGame": 9.35,
        "recYPG": 76.2,
        "tdPerGame": 0.6
      },
      "team": "KC",
      "year": 2021
    },
    {
      "eraNormFactor": 1.6786,
      "id": "p_00-0033873_KC_2021",
      "name": "Patrick Mahomes",
      "position": "QB",
      "rating": 93,
      "stats": {
        "avgINTPerGame": 0.8,
        "avgTDPerGame": 2.4,
        "completionPct": 0.6731,
        "passYPG": 294.8,
        "qbr": 100
      },
      "team": "KC",
      "year": 2021
    },
    {
      "eraNormFactor": 1.0,
      "id": "p_00-0034297_KC_2021",
      "name": "Byron Pringle",
      "position": "WR",
      "rating": 82,
      "stats": {
        "avgCatchesPerGame": 2.84,
        "avgTargetsPerGame": 4.05,
        "recYPG": 34.2,
        "tdPerGame": 0.421
      },
      "team": "KC",
      "year": 2021
    },
    {
      "eraNormFactor": 1.0,
      "id": "p_00-0034301_KC_2021",
      "name": "Darrel Williams",
      "position": "RB",
      "rating": 80,
      "stats": {
        "recYPG": 25.1,
        "rushAttPerGame": 8.06,
        "rushYPG": 31.2,
        "tdPerGame": 0.333
      },
      "team": "KC",
      "year": 2021
    },
    {
      "eraNormFactor": 1.0,
      "id": "p_00-0035140_KC_2021",
      "name": "Mecole Hardman",
      "position": "WR",
      "rating": 79,
      "stats": {
        "avgCatchesPerGame": 3.35,
        "avgTargetsPerGame": 4.6,
        "recYPG": 40.7,
        "tdPerGame": 0.15
      },
      "team": "KC",
      "year": 2021
    },
    {
      "eraNormFactor": 1.0,
      "id": "p_00-0035715_KC_2021",
      "name": "Derrick Gore",
      "position": "RB",
      "rating": 72,
      "stats": {
        "recYPG": 11.7,
        "rushAttPerGame": 6.0,
        "rushYPG": 28.8,
        "tdPerGame": 0.222
      },
      "team": "KC",
      "year": 2021
    },
    {
      "eraNormFactor": 1.0,
      "id": "p_00-0036360_KC_2021",
      "name": "Clyde Edwards-Helaire",
      "position": "RB",
      "rating": 83,
      "stats": {
        "recYPG": 11.8,
        "rushAttPerGame": 11.0,
        "rushYPG": 51.1,
        "tdPerGame": 0.333
      },
      "team": "KC",
      "year": 2021
    },
    {
      "eraNormFactor": 1.0,
      "id": "p_00-0033303_KC_2021",
      "name": "H.Butker",
      "position": "K",
      "rating": 84,
      "stats": {
        "avgKickDistance": 41.0,
        "avgMissDistance": 48.6,
        "fgAccuracy": 0.8649,
        "longestMadeKick": 56
      },
      "team": "KC",
      "year": 2021
    }
  ],
  "units": [
    {
      "eraNormFactor": 1.0,
      "id": "u_KC_OLine_2021",
      "position": "OLine",
      "rating": 83,
      "stats": {
        "normalizedRank": 7,
        "rushTDPct": 0.0357,
        "rushYPC": 4.73,
        "sacksAllowedPerGame": 2.5
      },
      "team": "KC",
      "year": 2021
    },
    {
      "eraNormFactor": 1.0,
      "id": "u_KC_DLine_2021",
      "position": "DLine",
      "rating": 64,
      "stats": {
        "blitzPct": 0.281,
        "normalizedRank": 21,
        "pressurePct": 0.262,
        "rushTDPerGameAllowed": 0.88,
        "rushYPCAllowed": 4.8,
        "rushYPGAllowed": 117.59,
        "sackPct": 0.0508
      },
      "team": "KC",
      "year": 2021
    },
    {
      "eraNormFactor": 1.0,
      "id": "u_KC_Secondary_2021",
      "position": "Secondary",
      "rating": 73,
      "stats": {
        "completionPctAllowed": 0.6574,
        "interceptionsPerGame": 0.88,
        "normalizedRank": 27,
        "passTDPerGameAllowed": 1.59,
        "passYPGAllowed": 251.35,
        "yardsPerAttemptAllowed": 6.7
      },
      "team": "KC",
      "year": 2021
    }
  ]
}
