{
  "players": [
    {
      "id": "p_00-0003035_CHI_2007",
      "name": "Desmond Clark",
      "position": "WR",
      "rating": 75,
      "stats": {
        "avgCatchesPerGame": 2.93,
        "avgTargetsPerGame": null,
        "recYPG": 36.3,
        "tdPerGame": 0.267
      },
      "team": "CHI",
      "year": 2007
    },
    {
      "id": "p_00-0006423_CHI_2007",
      "name": "Brian Griese",
      "position": "QB",
      "rating": 81,
      "stats": {
        "avgINTPerGame": 1.714,
        "avgTDPerGame": 1.429,
        "completionPct": 0.6145,
        "passYPG": 257.6,
        "qbr": 50.4
      },
      "team": "CHI",
      "year": 2007
    },
    {
      "id": "p_00-0011795_CHI_2007",
      "name": "Muhsin Muhammad",
      "position": "WR",
      "rating": 73,
      "stats": {
        "avgCatchesPerGame": 2.67,
        "avgTargetsPerGame": null,
        "recYPG": 38.0,
        "tdPerGame": 0.2
      },
      "team": "CHI",
      "year": 2007
    },
    {
      "id": "p_00-0021306_CHI_2007",
      "name": "Adrian Peterson",
      "position": "RB",
      "rating": 75,
      "stats": {
        "recYPG": 26.2,
        "rushAttPerGame": 9.44,
        "rushYPG": 31.9,
        "tdPerGame": 0.188
      },
      "team": "CHI",
      "year": 2007
    },
    {
      "id": "p_00-0022121_CHI_2007",
      "name": "Rex Grossman",
      "position": "QB",
      "rating": 66,
      "stats": {
        "avgINTPerGame": 0.875,
        "avgTDPerGame": 0.5,
        "completionPct": 0.5422,
        "passYPG": 176.4,
        "qbr": 0
      },
      "team": "CHI",
      "year": 2007
    },
    {
      "id": "p_00-0022807_CHI_2007",
      "name": "Bernard Berrian",
      "position": "WR",
      "rating": 87,
      "stats": {
        "avgCatchesPerGame": 4.38,
        "avgTargetsPerGame": null,
        "recYPG": 59.2,
        "tdPerGame": 0.312
      },
      "team": "CHI",
      "year": 2007
    },
    {
      "id": "p_00-0023439_CHI_2007",
      "name": "Cedric Benson",
      "position": "RB",
      "rating": 83,
      "stats": {
        "recYPG": 11.2,
        "rushAttPerGame": 17.91,
        "rushYPG": 61.6,
        "tdPerGame": 0.364
      },
      "team": "CHI",
      "year": 2007
    },
    {
      "id": "p_00-0024272_CHI_2007",
      "name": "Devin Hester",
      "position": "WR",
      "rating": 62,
      "stats": {
        "avgCatchesPerGame": 1.54,
        "avgTargetsPerGame": null,
        "recYPG": 23.0,
        "tdPerGame": 0.154
      },
      "team": "CHI",
      "year": 2007
    },
    {
      "id": "p_00-0025418_CHI_2007",
      "name": "Greg Olsen",
      "position": "WR",
      "rating": 70,
      "stats": {
        "avgCatchesPerGame": 3.25,
        "avgTargetsPerGame": null,
        "recYPG": 32.6,
        "tdPerGame": 0.167
      },
      "team": "CHI",
      "year": 2007
    },
    {
      "id": "p_00-0025480_CHI_2007",
      "name": "Garrett Wolfe",
      "position": "RB",
      "rating": 60,
      "stats": {
        "recYPG": 13.0,
        "rushAttPerGame": 3.44,
        "rushYPG": 9.4,
        "tdPerGame": 0.0
      },
      "team": "CHI",
      "year": 2007
    },
    {
      "id": "p_00-0023252_CHI_2007",
      "name": "R.Gould",
      "position": "K",
      "rating": 82,
      "stats": {
        "avgKickDistance": 37.4,
        "avgMissDistance": 46.4,
        "fgAccuracy": 0.8611,
        "longestMadeKick": 49
      },
      "team": "CHI",
      "year": 2007
    }
  ],
  "units": [
    {
      "id": "u_CHI_OLine_2007",
      "position": "OLine",
      "rating": 67,
      "stats": {
        "normalizedRank": 32,
        "rushTDPct": 0.0189,
        "rushYPC": 3.14,
        "sacksAllowedPerGame": 2.5
      },
      "team": "CHI",
      "year": 2007
    },
    {
      "id": "u_CHI_DLine_2007",
      "position": "DLine",
      "rating": 75,
      "stats": {
        "blitzPct": null,
        "normalizedRank": 24,
        "pressurePct": null,
        "rushTDPerGameAllowed": 1.06,
        "rushYPCAllowed": 4.3,
        "rushYPGAllowed": 122.94,
        "sackPct": 0.0758
      },
      "team": "CHI",
      "year": 2007
    },
    {
      "id": "u_CHI_Secondary_2007",
      "position": "Secondary",
      "rating": 72,
      "stats": {
        "completionPctAllowed": 0.634,
        "interceptionsPerGame": 1.0,
        "normalizedRank": 27,
        "passTDPerGameAllowed": 1.19,
        "passYPGAllowed": 231.75,
        "yardsPerAttemptAllowed": 6.4
      },
      "team": "CHI",
      "year": 2007
    }
  ]
}
