{
  "players": [
    {
      "id": "p_00-0007024_IND_2007",
      "name": "Marvin Harrison",
      "position": "WR",
      "team": "IND",
      "year": 2007,
      "stats": {
        "recYPG": 45.7,
        "tdPerGame": 0.167
      },
      "eraNormFactor": 1.0
    },
    {
      "id": "p_00-0010346_IND_2007",
      "name": "Peyton Manning",
      "position": "QB",
      "team": "IND",
      "year": 2007,
      "stats": {
        "passYPG": 261.3,
        "tdRatio": 0.0604,
        "intRatio": 0.0284,
        "qbr": 100
      },
      "eraNormFactor": 1.639
    },
    {
      "id": "p_00-0020498_IND_2007",
      "name": "Reggie Wayne",
      "position": "WR",
      "team": "IND",
      "year": 2007,
      "stats": {
        "recYPG": 93.3,
        "tdPerGame": 0.647
      },
      "eraNormFactor": 1.0,
      "is_all_pro": true
    },
    {
      "id": "p_00-0022165_IND_2007",
      "name": "Dallas Clark",
      "position": "WR",
      "team": "IND",
      "year": 2007,
      "stats": {
        "recYPG": 44.4,
        "tdPerGame": 0.75
      },
      "eraNormFactor": 1.0
    },
    {
      "id": "p_00-0022206_IND_2007",
      "name": "Kenton Keith",
      "position": "RB",
      "team": "IND",
      "year": 2007,
      "stats": {
        "rushYPG": 31.8,
        "tdPerGame": 0.176
      },
      "eraNormFactor": 1.0
    },
    {
      "id": "p_00-0022555_IND_2007",
      "name": "Ben Utecht",
      "position": "WR",
      "team": "IND",
      "year": 2007,
      "stats": {
        "recYPG": 27.4,
        "tdPerGame": 0.071
      },
      "eraNormFactor": 1.0
    },
    {
      "id": "p_00-0024245_IND_2007",
      "name": "Joseph Addai",
      "position": "RB",
      "team": "IND",
      "year": 2007,
      "stats": {
        "rushYPG": 69.7,
        "tdPerGame": 0.75
      },
      "eraNormFactor": 1.0
    },
    {
      "id": "p_00-0024698_IND_2007",
      "name": "Clifton Dawson",
      "position": "RB",
      "team": "IND",
      "year": 2007,
      "stats": {
        "rushYPG": 12.8,
        "tdPerGame": 0.2
      },
      "eraNormFactor": 1.0
    },
    {
      "id": "p_00-0025419_IND_2007",
      "name": "Anthony Gonzalez",
      "position": "WR",
      "team": "IND",
      "year": 2007,
      "stats": {
        "recYPG": 54.6,
        "tdPerGame": 0.333
      },
      "eraNormFactor": 1.0
    },
    {
      "id": "p_00-0016919_IND_2007",
      "name": "A.Vinatieri",
      "position": "K",
      "team": "IND",
      "year": 2007,
      "stats": {
        "fgAccuracy": 0.8
      },
      "eraNormFactor": 1.0
    }
  ],
  "units": [
    {
      "id": "u_IND_OLine_2007",
      "position": "OLine",
      "team": "IND",
      "year": 2007,
      "stats": {
        "sacksAllowedPerGame": 2.5,
        "rushYPC": 3.77,
        "rushTDPct": 0.0409,
        "normalizedRank": 25
      },
      "eraNormFactor": 1.0
    },
    {
      "id": "u_IND_DLine_2007",
      "position": "DLine",
      "team": "IND",
      "year": 2007,
      "stats": {
        "rushYPCAllowed": 3.8,
        "rushYPGAllowed": 106.94,
        "rushTDPerGameAllowed": 0.62,
        "sackPct": 0.0562,
        "blitzPct": 0.0,
        "pressurePct": 0.0,
        "normalizedRank": 15
      },
      "eraNormFactor": 1.0
    },
    {
      "id": "u_IND_Secondary_2007",
      "position": "Secondary",
      "team": "IND",
      "year": 2007,
      "stats": {
        "completionPctAllowed": 0.6526,
        "yardsPerAttemptAllowed": 5.3,
        "passYPGAllowed": 172.75,
        "passTDPerGameAllowed": 1.0,
        "interceptionsPerGame": 1.38,
        "normalizedRank": 2
      },
      "eraNormFactor": 1.0
    }
  ]
}
