{
  "players": [
    {
      "id": "p_00-0029319_CHI_2018",
      "name": "Josh Bellamy",
      "position": "WR",
      "team": "CHI",
      "year": 2018,
      "stats": {
        "recYPG": 10.8,
        "tdPerGame": 0.071
      },
      "eraNormFactor": 1.0
    },
    {
      "id": "p_00-0030710_CHI_2018",
      "name": "Trey Burton",
      "position": "WR",
      "team": "CHI",
      "year": 2018,
      "stats": {
        "recYPG": 35.6,
        "tdPerGame": 0.375
      },
      "eraNormFactor": 1.0
    },
    {
      "id": "p_00-0031228_CHI_2018",
      "name": "Taylor Gabriel",
      "position": "WR",
      "team": "CHI",
      "year": 2018,
      "stats": {
        "recYPG": 42.6,
        "tdPerGame": 0.118
      },
      "eraNormFactor": 1.0
    },
    {
      "id": "p_00-0031428_CHI_2018",
      "name": "Allen Robinson",
      "position": "WR",
      "team": "CHI",
      "year": 2018,
      "stats": {
        "recYPG": 64.1,
        "tdPerGame": 0.357
      },
      "eraNormFactor": 1.0
    },
    {
      "id": "p_00-0032780_CHI_2018",
      "name": "Jordan Howard",
      "position": "RB",
      "team": "CHI",
      "year": 2018,
      "stats": {
        "rushYPG": 57.1,
        "tdPerGame": 0.529
      },
      "eraNormFactor": 1.0
    },
    {
      "id": "p_00-0033556_CHI_2018",
      "name": "Tarik Cohen",
      "position": "RB",
      "team": "CHI",
      "year": 2018,
      "stats": {
        "rushYPG": 26.1,
        "tdPerGame": 0.176
      },
      "eraNormFactor": 1.0
    },
    {
      "id": "p_00-0033869_CHI_2018",
      "name": "Mitchell Trubisky",
      "position": "QB",
      "team": "CHI",
      "year": 2018,
      "stats": {
        "passYPG": 235.1,
        "tdRatio": 0.0524,
        "intRatio": 0.0252,
        "qbr": 87.3
      },
      "eraNormFactor": 1.2048
    },
    {
      "id": "p_00-0034353_CHI_2018",
      "name": "Anthony Miller",
      "position": "WR",
      "team": "CHI",
      "year": 2018,
      "stats": {
        "recYPG": 30.5,
        "tdPerGame": 0.467
      },
      "eraNormFactor": 1.0
    },
    {
      "id": "p_00-0030850_CHI_2018",
      "name": "C.Parkey",
      "position": "K",
      "team": "CHI",
      "year": 2018,
      "stats": {
        "fgAccuracy": 0.7647
      },
      "eraNormFactor": 1.0
    }
  ],
  "units": [
    {
      "id": "u_CHI_OLine_2018",
      "position": "OLine",
      "team": "CHI",
      "year": 2018,
      "stats": {
        "sacksAllowedPerGame": 2.5,
        "rushYPC": 4.12,
        "rushTDPct": 0.0329,
        "normalizedRank": 27
      },
      "eraNormFactor": 1.0
    },
    {
      "id": "u_CHI_DLine_2018",
      "position": "DLine",
      "team": "CHI",
      "year": 2018,
      "stats": {
        "sacksPerGame": 3.0,
        "rushYPCAllowed": 3.64,
        "rushTDPctAllowed": 0.0138,
        "normalizedRank": 3
      },
      "eraNormFactor": 1.0
    },
    {
      "id": "u_CHI_Secondary_2018",
      "position": "Secondary",
      "team": "CHI",
      "year": 2018,
      "stats": {
        "completionPctAllowed": 0.563,
        "yardsPerAttemptAllowed": 5.77,
        "tdPctAllowed": 0.0336,
        "intPct": 0.0406,
        "normalizedRank": 1
      },
      "eraNormFactor": 1.0
    }
  ]
}