{
  "players": [
    {
      "id": "p_00-0023436_KC_2014",
      "name": "Alex Smith",
      "position": "QB",
      "rating": 81,
      "stats": {
        "avgINTPerGame": 0.4,
        "avgTDPerGame": 1.2,
        "completionPct": 0.653,
        "passYPG": 217.7,
        "qbr": 92.3
      },
      "team": "KC",
      "year": 2014
    },
    {
      "id": "p_00-0024268_KC_2014",
      "name": "Anthony Fasano",
      "position": "WR",
      "rating": 68,
      "stats": {
        "avgCatchesPerGame": 1.79,
        "avgTargetsPerGame": 2.57,
        "recYPG": 16.1,
        "tdPerGame": 0.286
      },
      "team": "KC",
      "year": 2014
    },
    {
      "id": "p_00-0025410_KC_2014",
      "name": "Dwayne Bowe",
      "position": "WR",
      "rating": 78,
      "stats": {
        "avgCatchesPerGame": 4.0,
        "avgTargetsPerGame": 6.33,
        "recYPG": 50.3,
        "tdPerGame": 0.0
      },
      "team": "KC",
      "year": 2014
    },
    {
      "id": "p_00-0026173_KC_2014",
      "name": "Donnie Avery",
      "position": "WR",
      "rating": 71,
      "stats": {
        "avgCatchesPerGame": 3.0,
        "avgTargetsPerGame": 5.2,
        "recYPG": 35.2,
        "tdPerGame": 0.0
      },
      "team": "KC",
      "year": 2014
    },
    {
      "id": "p_00-0026213_KC_2014",
      "name": "Jamaal Charles",
      "position": "RB",
      "rating": 93,
      "stats": {
        "recYPG": 19.4,
        "rushAttPerGame": 13.73,
        "rushYPG": 68.9,
        "tdPerGame": 0.6
      },
      "team": "KC",
      "year": 2014
    },
    {
      "id": "p_00-0029311_KC_2014",
      "name": "Junior Hemingway",
      "position": "WR",
      "rating": 57,
      "stats": {
        "avgCatchesPerGame": 1.33,
        "avgTargetsPerGame": 2.33,
        "recYPG": 12.0,
        "tdPerGame": 0.0
      },
      "team": "KC",
      "year": 2014
    },
    {
      "id": "p_00-0030280_KC_2014",
      "name": "Knile Davis",
      "position": "RB",
      "rating": 78,
      "stats": {
        "recYPG": 9.8,
        "rushAttPerGame": 8.93,
        "rushYPG": 30.9,
        "tdPerGame": 0.4
      },
      "team": "KC",
      "year": 2014
    },
    {
      "id": "p_00-0030506_KC_2014",
      "name": "Travis Kelce",
      "position": "WR",
      "rating": 87,
      "stats": {
        "avgCatchesPerGame": 4.19,
        "avgTargetsPerGame": 5.44,
        "recYPG": 53.9,
        "tdPerGame": 0.312
      },
      "team": "KC",
      "year": 2014
    },
    {
      "id": "p_00-0030669_KC_2014",
      "name": "Albert Wilson",
      "position": "WR",
      "rating": 70,
      "stats": {
        "avgCatchesPerGame": 2.29,
        "avgTargetsPerGame": 4.0,
        "recYPG": 37.1,
        "tdPerGame": 0.0
      },
      "team": "KC",
      "year": 2014
    },
    {
      "id": "p_00-0031060_KC_2014",
      "name": "De'Anthony Thomas",
      "position": "WR",
      "rating": 59,
      "stats": {
        "avgCatchesPerGame": 1.92,
        "avgTargetsPerGame": 2.58,
        "recYPG": 13.0,
        "tdPerGame": 0.0
      },
      "team": "KC",
      "year": 2014
    },
    {
      "id": "p_00-0031203_KC_2014",
      "name": "C.Santos",
      "position": "K",
      "rating": 71,
      "stats": {
        "avgKickDistance": 35.1,
        "avgMissDistance": 45.2,
        "fgAccuracy": 0.8333,
        "longestMadeKick": 53
      },
      "team": "KC",
      "year": 2014
    }
  ],
  "units": [
    {
      "id": "u_KC_OLine_2014",
      "position": "OLine",
      "rating": 89,
      "stats": {
        "normalizedRank": 5,
        "rushTDPct": 0.0429,
        "rushYPC": 4.57,
        "sacksAllowedPerGame": 2.5
      },
      "team": "KC",
      "year": 2014
    },
    {
      "id": "u_KC_DLine_2014",
      "position": "DLine",
      "rating": 78,
      "stats": {
        "blitzPct": null,
        "normalizedRank": 28,
        "pressurePct": null,
        "rushTDPerGameAllowed": 0.25,
        "rushYPCAllowed": 4.7,
        "rushYPGAllowed": 127.25,
        "sackPct": 0.0844
      },
      "team": "KC",
      "year": 2014
    },
    {
      "id": "u_KC_Secondary_2014",
      "position": "Secondary",
      "rating": 87,
      "stats": {
        "completionPctAllowed": 0.5835,
        "interceptionsPerGame": 0.38,
        "normalizedRank": 2,
        "passTDPerGameAllowed": 1.38,
        "passYPGAllowed": 203.25,
        "yardsPerAttemptAllowed": 5.5
      },
      "team": "KC",
      "year": 2014
    }
  ]
}
